main.py
airmcp-0.1.0.dist-info/METADATA
airmcp-0.1.0.dist-info/WHEEL
airmcp-0.1.0.dist-info/top_level.txt
airmcp-0.1.0.dist-info/RECORD
