Metadata-Version: 2.4
Name: airmcp
Version: 0.1.0
Summary: Add your description here
Requires-Python: >=3.13
Requires-Dist: air[standard]>=0.21.0
Requires-Dist: fastmcp>=2.11.3
